jump/__init__.py
jump/menu.py
pyjump-1.2.dist-info/LICENSE.md
pyjump-1.2.dist-info/METADATA
pyjump-1.2.dist-info/WHEEL
pyjump-1.2.dist-info/entry_points.txt
pyjump-1.2.dist-info/top_level.txt
pyjump-1.2.dist-info/RECORD
