Metadata-Version: 2.1
Name: pyjump
Version: 1.2
Summary: Utility that builds a 2-level menu based on applications and their available environments.
Home-page: https://github.com/opper/jump
Author: opper
Author-email: alex@opper.nl
License: UNKNOWN
Platform: UNKNOWN
Classifier: Programming Language :: Python :: 3
Classifier: Programming Language :: Python :: 3.7
Classifier: License :: OSI Approved :: MIT License
Classifier: Operating System :: OS Independent
Requires-Dist: python-dotenv
Requires-Dist: pythondialog
Requires-Dist: requests
Requires-Dist: click
